setup.py
power/__init__.py
power/common.py
power/darwin.py
power/freebsd.py
power/linux.py
power/tests.py
power/win32.py
power.egg-info/PKG-INFO
power.egg-info/SOURCES.txt
power.egg-info/dependency_links.txt
power.egg-info/requires.txt
power.egg-info/top_level.txt