Metadata-Version: 1.1
Name: power
Version: 1.4
Summary: Cross-platform system power status information.
Home-page: https://github.com/Kentzo/Power
Author: Ilya Kulakov
Author-email: kulakov.ilya@gmail.com
License: MIT License
Platform: Mac OS X 10.6+
Platform: Windows XP+
Platform: Linux 2.6+
Platform: FreeBSD
Classifier: Intended Audience :: Developers
Classifier: Intended Audience :: System Administrators
Classifier: License :: OSI Approved :: MIT License
Classifier: Natural Language :: English
Classifier: Operating System :: MacOS :: MacOS X
Classifier: Operating System :: Microsoft :: Windows
Classifier: Operating System :: POSIX :: Linux
Classifier: Programming Language :: Python
Classifier: Topic :: System :: Monitoring
Classifier: Topic :: System :: Power (UPS)
